xorius/__init__.py
xorius/cli.py
xorius-0.0.4.dist-info/METADATA
xorius-0.0.4.dist-info/WHEEL
xorius-0.0.4.dist-info/entry_points.txt
xorius-0.0.4.dist-info/top_level.txt
xorius-0.0.4.dist-info/RECORD
