Metadata-Version: 2.1
Name: xorius
Version: 0.0.4
Summary: A LLM-based agent.
Author-email: Linusp <linusp1024@gmail.com>
License: MIT
Project-URL: Homepage, https://github.com/monsternlp/xorius
Classifier: License :: OSI Approved :: MIT License
Classifier: Programming Language :: Python
Classifier: Programming Language :: Python :: 3
Requires-Python: >=3.8
Requires-Dist: pydantic
Requires-Dist: click
Requires-Dist: rich
Requires-Dist: tiktoken
Requires-Dist: ullm >=0.1.3
Provides-Extra: test
Requires-Dist: pytest ; extra == 'test'
Requires-Dist: pytest-cov ; extra == 'test'
